Metadata-Version: 2.1
Name: guigebacktest
Version: 0.0.4
Summary: a backtest system
Home-page: UNKNOWN
Author: guige
Author-email: pangtongqing@guigeinvest.com
License: MIT
Platform: UNKNOWN
Classifier: Programming Language :: Python :: 3
Classifier: License :: OSI Approved :: MIT License
Classifier: Operating System :: OS Independent
Requires-Python: >=3.6
